graphene_django_ai/__init__.py
graphene_django_ai/converter.py
graphene_django_ai/utils.py
graphene_django_ai/forms/__init__.py
graphene_django_ai/forms/converter.py
graphene_django_ai/forms/mutations.py
graphene_django_ai/forms/tests/__init__.py
graphene_django_ai/forms/tests/test_converter.py
graphene_django_ai/schemes/__init__.py
graphene_django_ai/schemes/mutations.py
graphene_django_ai/tests/__init__.py
graphene_django_ai/tests/base_test.py
graphene_django_ai-1.0.8.dist-info/LICENSE.md
graphene_django_ai-1.0.8.dist-info/METADATA
graphene_django_ai-1.0.8.dist-info/WHEEL
graphene_django_ai-1.0.8.dist-info/dependency_links.txt
graphene_django_ai-1.0.8.dist-info/top_level.txt
graphene_django_ai-1.0.8.dist-info/RECORD
