Metadata-Version: 2.1
Name: graphene-django-ai
Version: 1.0.8
Summary: Toolbox for changes to streamline graphene-django.
Home-page: https://github.com/ambient-innovation/graphene-django-ai
Author: Ambient Innovation: GmbH
Author-email: hello@ambient-innovation.com
License: The MIT License (MIT)
Platform: UNKNOWN
Requires-Dist: django (>=2.0.0)
Requires-Dist: graphene-django (>=2.2.0)
Requires-Dist: django-graphql-jwt (>=0.2.1)
